pyros_msgs/__init__.py
pyros_msgs/_version.py
pyros_msgs/msg/OptionalFields.msg
pyros_msgs/opt_as_array/__init__.py
pyros_msgs/opt_as_array/opt_as_array.py
pyros_msgs/opt_as_array/ros_mappings.py
pyros_msgs/opt_as_nested/__init__.py
pyros_msgs/opt_as_nested/opt_as_nested.py
pyros_msgs/opt_as_nested/ros_mappings.py
pyros_msgs/typecheck/__init__.py
pyros_msgs/typecheck/ros_mappings.py
pyros_msgs/typecheck/typechecker.py
pyros_msgs-0.2.0.dist-info/DESCRIPTION.rst
pyros_msgs-0.2.0.dist-info/METADATA
pyros_msgs-0.2.0.dist-info/RECORD
pyros_msgs-0.2.0.dist-info/WHEEL
pyros_msgs-0.2.0.dist-info/metadata.json
pyros_msgs-0.2.0.dist-info/pbr.json
pyros_msgs-0.2.0.dist-info/top_level.txt
