Metadata-Version: 2.0
Name: pyros-msgs
Version: 0.2.0
Summary: Pyros messages and services definition
Home-page: http://github.com/asmodehn/pyros-msgs
Author: AlexV
Author-email: asmodehn@gmail.com
License: MIT
Platform: UNKNOWN
Requires-Dist: six
Requires-Dist: pyyaml (>=3.10)
